markdown_mermaid_cli/__init__.py
markdown_mermaid_cli/extension.py
markdown_mermaid_cli/puppeteer-config.json
markdown_mermaid_cli-0.3.0.dist-info/METADATA
markdown_mermaid_cli-0.3.0.dist-info/WHEEL
markdown_mermaid_cli-0.3.0.dist-info/licenses/LICENSE
markdown_mermaid_cli-0.3.0.dist-info/RECORD
