Metadata-Version: 2.4
Name: markdown-mermaid-cli
Version: 0.3.0
Summary: Mermaid extension for Python-Markdown using mermaid-cli.
Project-URL: Homepage, https://github.com/hkato/markdown-mermaid-cli
Project-URL: Documentation, https://hkato.github.io/markdown-mermaid-cli/
Project-URL: Repository, https://github.com/hkato/markdown-mermaid-cli
Project-URL: Issues, https://github.com/hkato/markdown-mermaid-cli/issues
Project-URL: Changelog, https://github.com/hkato/markdown-mermaid-cli/blob/main/CHANGELOG.md
Author-email: Hideyuki KATO <hideyuki@kato.jp>
License-Expression: MIT
License-File: LICENSE
Keywords: markdown,mermaid,mkdocs
Classifier: Development Status :: 4 - Beta
Classifier: Intended Audience :: Developers
Classifier: Programming Language :: Python :: 3
Classifier: Programming Language :: Python :: 3.9
Classifier: Programming Language :: Python :: 3.10
Classifier: Programming Language :: Python :: 3.11
Classifier: Programming Language :: Python :: 3.12
Classifier: Programming Language :: Python :: 3.13
Classifier: Topic :: Documentation
Classifier: Topic :: Software Development :: Documentation
Requires-Python: >=3.9
Requires-Dist: markdown>=3.8
